<?xml version="1.0" encoding="utf-8"?>
<MapIconData xmlns:xsd="http://www.w3.org/2001/XMLSchema" xmlns:xsi="http://www.w3.org/2001/XMLSchema-instance">
  <dataName>mapIcon0107</dataName>
  <netOpenName>
    <id>870</id>
    <str>v1_40 16_1</str>
    <data />
  </netOpenName>
  <disableFlag>false</disableFlag>
  <name>
    <id>107</id>
    <str>九重 永遠</str>
    <data />
  </name>
  <sortName>コ</sortName>
  <image>
    <path>CHU_UI_MapIcon_00000107.dds</path>
  </image>
  <defaultHave>true</defaultHave>
  <explainText>A910からのプレゼント</explainText>
  <priority>0</priority>
</MapIconData>